{
    "version": 6,
    "cmakeMinimumRequired": {
        "major": 3,
        "minor": 23,
        "patch": 0
    },
    "configurationPresets": [
        {
            "name": "default",
            "generator": "Ninja",
            "binaryDir": "${sourceDir}/build",
            "cacheVariables": [
                {
                    "name": "CMAKE_TOOLCHAIN_FILE",
                    "value": "$env{VCPKG_ROOT}/scripts/buildsystems/vcpkg.cmake"
                }
            ]
        }
    ],
    "configurePresets": [
        {
            "name": "msvc",
            "displayName": "Visual Studio Community 2022 Release - amd64",
            "description": "Using compilers for Visual Studio 17 2022 (x64 architecture)",
            "generator": "Visual Studio 17 2022",
            "toolset": "host=x64",
            "architecture": "x64",
            "binaryDir": "${sourceDir}/out/build/${presetName}",
            "cacheVariables": {
                "CMAKE_INSTALL_PREFIX": "${sourceDir}/out/install/${presetName}",
                "CMAKE_C_COMPILER": "cl.exe",
                "CMAKE_CXX_COMPILER": "cl.exe"
            }
        },
        {
            "name": "default",
            "displayName": "Configure preset using toolchain file",
            "description": "Sets Ninja generator, build and install directory",
            "generator": "Ninja",
            "binaryDir": "${sourceDir}/out/build/${presetName}",
            "cacheVariables": {
                "CMAKE_BUILD_TYPE": "Debug",
                "CMAKE_TOOLCHAIN_FILE": "",
                "CMAKE_INSTALL_PREFIX": "${sourceDir}/out/install/${presetName}"
            }
        },
        {
            "name": "msvc_x64_x86",
            "displayName": "Visual Studio Community 2022 Release - amd64_x86",
            "description": "Using compilers for Visual Studio 17 2022 (x64_x86 architecture)",
            "generator": "Visual Studio 17 2022",
            "toolset": "host=x64",
            "architecture": "win32",
            "binaryDir": "${sourceDir}/out/build/${presetName}",
            "cacheVariables": {
                "CMAKE_INSTALL_PREFIX": "${sourceDir}/out/install/${presetName}",
                "CMAKE_C_COMPILER": "cl.exe",
                "CMAKE_CXX_COMPILER": "cl.exe"
            }
        }
    ],
    "buildPresets": [
        {
            "name": "msvc-debug",
            "displayName": "Visual Studio Community 2022 Release - amd64 - Debug",
            "configurePreset": "msvc",
            "configuration": "Debug"
        },
        {
            "name": "msvc_x64_x86-debug",
            "displayName": "Visual Studio Community 2022 Release - amd64_x86 - Debug",
            "configurePreset": "msvc_x64_x86",
            "configuration": "Debug"
        }
    ]
}